ALU/logic/and/and3.vhdl
library IEEE;
use IEEE.std_logic_1164.all;

entity AND3 is
    port(
        a, b, c : in std_logic;
        d       : out std_logic
    );
end AND3;

architecture BEHAVE of AND3 is
begin
    d <= a and (not b) and c;
end BEHAVE;

ALU/and3_tb.vhdl
-- Test Bench
LIBRARY IEEE;
USE ieee.std_logic_1164.ALL;

ENTITY and3_tb IS
END and3_tb;

ARCHITECTURE test OF and3_tb IS
    COMPONENT AND3 IS
        PORT (
            a, b, c : IN std_logic;
            d : OUT std_logic
        );
    END COMPONENT;

    SIGNAL a_signal, b_signal, c_signal, d_signal : std_logic;

BEGIN
    and3_cell : AND3 PORT MAP(
        -- connect ports to signals
        a => a_signal,
        b => b_signal,
        c => c_signal,
        d => d_signal
    );

    PROCESS BEGIN

        a_signal <= '0';
        b_signal <= '0';
        c_signal <= '0';
        WAIT FOR 1 ns;

        a_signal <= '0';
        b_signal <= '0';
        c_signal <= '1';
        WAIT FOR 1 ns;

        a_signal <= '0';
        b_signal <= '1';
        c_signal <= '0';
        WAIT FOR 1 ns;

        a_signal <= '0';
        b_signal <= '1';
        c_signal <= '1';
        WAIT FOR 1 ns;

        a_signal <= '1';
        b_signal <= '0';
        c_signal <= '0';
        WAIT FOR 1 ns;

        a_signal <= '1';
        b_signal <= '0';
        c_signal <= '1';
        WAIT FOR 1 ns;

        a_signal <= '1';
        b_signal <= '1';
        c_signal <= '0';
        WAIT FOR 1 ns;

        a_signal <= '1';
        b_signal <= '1';
        c_signal <= '1';
        WAIT FOR 1 ns;

        ASSERT false REPORT "Reached end of test";
        WAIT;

    END PROCESS;
END test;

ALU/logic/and/and3/and3.vcd
$date
  Tue Jun  2 14:24:03 2020
$end
$version
  GHDL v0
$end
$timescale
  1 fs
$end
$scope module standard $end
$upscope $end
$scope module std_logic_1164 $end
$upscope $end
$scope module and3_tb $end
$var reg 1 ! a_signal $end
$var reg 1 " b_signal $end
$var reg 1 # c_signal $end
$var reg 1 $ d_signal $end
$scope module and3_cell $end
$var reg 1 % a $end
$var reg 1 & b $end
$var reg 1 ' c $end
$var reg 1 ( d $end
$upscope $end
$upscope $end
$enddefinitions $end
#0
0!
0"
0#
0$
0%
0&
0'
0(
#1000000
1#
1'
#2000000
1"
0#
1&
0'
#3000000
1#
1'
#4000000
1!
0"
0#
1%
0&
0'
#5000000
1#
1$
1'
1(
#6000000
1"
0#
0$
1&
0'
0(
#7000000
1#
1'
