ALU/mux8to1.vhdl
library IEEE;
use IEEE.std_logic_1164.all;

entity MUX8TO1 is
    port(
        a0, a1, a2, a3, a4, a5, a6, a7 : in std_logic;
        sel  : in std_logic_vector(2 downto 0);
        c    : out std_logic
    );
end MUX8TO1;

architecture BEHAVE of MUX8TO1 is
begin
    with sel select
        c <= a0 when "000",
             a1 when "001",
             a2 when "010",
             a3 when "011",
             a4 when "100",
             a5 when "101",
             a6 when "110",
             a7 when "111",
             '0'  when others;             
end BEHAVE;

ALU/plexer/mux8to1/mux8to1_tb.vhdl
-- Test Bench
LIBRARY IEEE;
USE ieee.std_logic_1164.ALL;

ENTITY mux8to1_tb IS
END mux8to1_tb;

ARCHITECTURE test OF mux8to1_tb IS
    COMPONENT MUX8TO1 IS
        PORT (
            a0, a1, a2, a3, a4, a5, a6, a7 : IN std_logic;
            sel : IN std_logic_vector(2 DOWNTO 0);
            c : OUT std_logic
        );
    END COMPONENT;

    SIGNAL a0_signal, a1_signal, a2_signal, a3_signal, a4_signal, 
    a5_signal, a6_signal, a7_signal, c_signal : std_logic;
    SIGNAL sel_signal : std_logic_vector(2 DOWNTO 0);

BEGIN
    alu_mux8to1 : mux8to1 PORT MAP(
        -- connect ports to signals
        a0 => a0_signal, a1 => a1_signal, a2 => a2_signal, 
        a3 => a3_signal, a4 => a4_signal, a5 => a5_signal, 
        a6 => a6_signal, a7 => a7_signal,
        sel => sel_signal,
        c => c_signal
    );

    PROCESS BEGIN

        a0_signal <= '1';
        a1_signal <= '0';
        a2_signal <= '0';
        a3_signal <= '0';
        a4_signal <= '0';
        a5_signal <= '0';
        a6_signal <= '0';
        a7_signal <= '0';
        sel_signal <= "000";
        WAIT FOR 1 ns;

        a0_signal <= '0';
        a1_signal <= '1';
        a2_signal <= '0';
        a3_signal <= '0';
        a4_signal <= '0';
        a5_signal <= '0';
        a6_signal <= '0';
        a7_signal <= '0';
        sel_signal <= "001";
        WAIT FOR 1 ns;

        a0_signal <= '0';
        a1_signal <= '0';
        a2_signal <= '1';
        a3_signal <= '0';
        a4_signal <= '0';
        a5_signal <= '0';
        a6_signal <= '0';
        a7_signal <= '0';
        sel_signal <= "010";
        WAIT FOR 1 ns;

        a0_signal <= '0';
        a1_signal <= '0';
        a2_signal <= '0';
        a3_signal <= '1';
        a4_signal <= '0';
        a5_signal <= '0';
        a6_signal <= '0';
        a7_signal <= '0';
        sel_signal <= "011";
        WAIT FOR 1 ns;

        a0_signal <= '0';
        a1_signal <= '0';
        a2_signal <= '0';
        a3_signal <= '0';
        a4_signal <= '1';
        a5_signal <= '0';
        a6_signal <= '0';
        a7_signal <= '0';
        sel_signal <= "100";
        WAIT FOR 1 ns;

        a0_signal <= '0';
        a1_signal <= '0';
        a2_signal <= '0';
        a3_signal <= '0';
        a4_signal <= '0';
        a5_signal <= '1';
        a6_signal <= '0';
        a7_signal <= '0';
        sel_signal <= "101";
        WAIT FOR 1 ns;

        a0_signal <= '0';
        a1_signal <= '0';
        a2_signal <= '0';
        a3_signal <= '0';
        a4_signal <= '0';
        a5_signal <= '0';
        a6_signal <= '1';
        a7_signal <= '0';
        sel_signal <= "110";
        WAIT FOR 1 ns;

        a0_signal <= '0';
        a1_signal <= '0';
        a2_signal <= '0';
        a3_signal <= '0';
        a4_signal <= '0';
        a5_signal <= '0';
        a6_signal <= '0';
        a7_signal <= '1';
        sel_signal <= "111";
        WAIT FOR 1 ns;

        ASSERT false REPORT "Reached end of test";
        WAIT;

    END PROCESS;
END test;

ALU/plexer/mux8to1/mux8to1.vcd
$date
  Wed Jun  3 19:31:57 2020
$end
$version
  GHDL v0
$end
$timescale
  1 fs
$end
$scope module standard $end
$upscope $end
$scope module std_logic_1164 $end
$upscope $end
$scope module mux8to1_tb $end
$var reg 1 ! a0_signal $end
$var reg 1 " a1_signal $end
$var reg 1 # a2_signal $end
$var reg 1 $ a3_signal $end
$var reg 1 % a4_signal $end
$var reg 1 & a5_signal $end
$var reg 1 ' a6_signal $end
$var reg 1 ( a7_signal $end
$var reg 1 ) c_signal $end
$var reg 3 * sel_signal[2:0] $end
$scope module alu_mux8to1 $end
$var reg 1 + a0 $end
$var reg 1 , a1 $end
$var reg 1 - a2 $end
$var reg 1 . a3 $end
$var reg 1 / a4 $end
$var reg 1 0 a5 $end
$var reg 1 1 a6 $end
$var reg 1 2 a7 $end
$var reg 3 3 sel[2:0] $end
$var reg 1 4 c $end
$upscope $end
$upscope $end
$enddefinitions $end
#0
1!
0"
0#
0$
0%
0&
0'
0(
1)
b000 *
1+
0,
0-
0.
0/
00
01
02
b000 3
14
#1000000
0!
1"
b001 *
0+
1,
b001 3
#2000000
0"
1#
b010 *
0,
1-
b010 3
#3000000
0#
1$
b011 *
0-
1.
b011 3
#4000000
0$
1%
b100 *
0.
1/
b100 3
#5000000
0%
1&
b101 *
0/
10
b101 3
#6000000
0&
1'
b110 *
00
11
b110 3
#7000000
0'
1(
b111 *
01
12
b111 3
